etherollapp/CHANGELOG.md
etherollapp/sentry_utils.py
etherollapp/testsuite.py
etherollapp/version.py
etherollapp/etheroll/about.kv
etherollapp/etheroll/about.py
etherollapp/etheroll/addressbutton.py
etherollapp/etheroll/constants.py
etherollapp/etheroll/controller.kv
etherollapp/etheroll/controller.py
etherollapp/etheroll/createnewaccount.kv
etherollapp/etheroll/createnewaccount.py
etherollapp/etheroll/customtoolbar.kv
etherollapp/etheroll/customtoolbar.py
etherollapp/etheroll/flashqrcode.kv
etherollapp/etheroll/flashqrcode.py
etherollapp/etheroll/importkeystore.kv
etherollapp/etheroll/importkeystore.py
etherollapp/etheroll/lazyscreenmanager.py
etherollapp/etheroll/passwordform.kv
etherollapp/etheroll/passwordform.py
etherollapp/etheroll/roll.kv
etherollapp/etheroll/roll.py
etherollapp/etheroll/roll_results.kv
etherollapp/etheroll/roll_results.py
etherollapp/etheroll/scroll_view_spinner.kv
etherollapp/etheroll/scroll_view_spinner.py
etherollapp/etheroll/scrollablelabel.kv
etherollapp/etheroll/scrollablelabel.py
etherollapp/etheroll/send.kv
etherollapp/etheroll/send.py
etherollapp/etheroll/settings.py
etherollapp/etheroll/settings_screen.kv
etherollapp/etheroll/settings_screen.py
etherollapp/etheroll/store.py
etherollapp/etheroll/switchaccount.kv
etherollapp/etheroll/switchaccount.py
etherollapp/etheroll/ui_utils.py
etherollapp/etheroll/utils.py
etherollapp/osc/README.md
etherollapp/osc/__init__.py
etherollapp/osc/osc_app_client.py
etherollapp/osc/osc_app_server.py
etherollapp/service/__init__.py
etherollapp/service/main.py
etherollapp/service/utils.py
etherollapp/tests/__init__.py
etherollapp/tests/test_import.py
etherollapp/tests/utils.py
etherollapp/tests/etheroll/__init__.py
etherollapp/tests/etheroll/test_settings.py
etherollapp/tests/etheroll/test_utils.py
etherollapp/tests/service/test_main.py
etherollapp/tests/service/test_utils.py
etherollapp/tests/ui/README.md
etherollapp/tests/ui/__init__.py
etherollapp/tests/ui/test_etheroll_ui.py
EtherollApp-2020.322.dist-info/LICENSE
EtherollApp-2020.322.dist-info/METADATA
EtherollApp-2020.322.dist-info/WHEEL
EtherollApp-2020.322.dist-info/entry_points.txt
EtherollApp-2020.322.dist-info/top_level.txt
EtherollApp-2020.322.dist-info/RECORD
