Metadata-Version: 2.1
Name: EtherollApp
Version: 2020.322
Summary: Provably fair dice game running on the Ethereum blockchain
Home-page: https://github.com/AndreMiras/EtherollApp
Author: Andre Miras
License: UNKNOWN
Platform: UNKNOWN
Requires-Python: >=3
Requires-Dist: eth-account (<=0.4.0)
Requires-Dist: eth-utils
Requires-Dist: kivy-garden.kivymd
Requires-Dist: layoutmargin
Requires-Dist: oscpy
Requires-Dist: pyetheroll (>=20200320)
Requires-Dist: python-dotenv
Requires-Dist: raven
Requires-Dist: requests-cache
Requires-Dist: web3
